MANIFEST.in
README.rst
setup.py
pluct/__init__.py
pluct/datastructures.py
pluct/exceptions.py
pluct/resource.py
pluct/schema.py
pluct/session.py
pluct.egg-info/PKG-INFO
pluct.egg-info/SOURCES.txt
pluct.egg-info/dependency_links.txt
pluct.egg-info/requires.txt
pluct.egg-info/top_level.txt