Metadata-Version: 1.1
Name: pluct
Version: 1.2.2
Summary: JSON Hyper Schema client
Home-page: https://github.com/globocom/pluct
Author: Marcos Daniel Petry
Author-email: marcospetry@gmail.com
License: UNKNOWN
Platform: UNKNOWN
Classifier: Development Status :: 4 - Beta
Classifier: Environment :: No Input/Output (Daemon)
Classifier: Intended Audience :: Developers
Classifier: License :: OSI Approved :: MIT License
Classifier: Operating System :: Unix
Classifier: Programming Language :: Python :: 2.7
